klein_bottle/__init__.py
klein_bottle-0.0.1.dist-info/METADATA
klein_bottle-0.0.1.dist-info/WHEEL
klein_bottle-0.0.1.dist-info/licenses/LICENSE
klein_bottle-0.0.1.dist-info/RECORD
